julia_browser/__init__.py
julia_browser/agent_sdk.py
julia_browser/browser_sdk.py
julia_browser/cli.py
julia_browser/cli_interface.py
julia_browser/main.py
julia_browser/browser/__init__.py
julia_browser/browser/aria_accessibility_extractor.py
julia_browser/browser/content_analysis_apis.py
julia_browser/browser/content_analysis_apis_v2.py
julia_browser/browser/content_filter.py
julia_browser/browser/css_generated_content.py
julia_browser/browser/css_layout_calculator.py
julia_browser/browser/css_media_query_extractor.py
julia_browser/browser/css_parser.py
julia_browser/browser/dynamic_content_detector.py
julia_browser/browser/engine.py
julia_browser/browser/form_validation_extractor.py
julia_browser/browser/interactive_forms.py
julia_browser/browser/js_engine.py
julia_browser/browser/layout_engine.py
julia_browser/browser/mathml_svg_extractor.py
julia_browser/browser/performance_cache.py
julia_browser/browser/real_js_apis.py
julia_browser/browser/renderer.py
julia_browser/browser/web_components_extractor.py
julia_browser/proxy/__init__.py
julia_browser/proxy/interceptor.py
julia_browser-2.1.0.dist-info/licenses/LICENSE
julia_browser-2.1.0.dist-info/METADATA
julia_browser-2.1.0.dist-info/WHEEL
julia_browser-2.1.0.dist-info/entry_points.txt
julia_browser-2.1.0.dist-info/top_level.txt
julia_browser-2.1.0.dist-info/RECORD
