Metadata-Version: 2.4
Name: julia-browser
Version: 2.1.0
Summary: A comprehensive Python-based CLI web browser with JavaScript support and modern web compatibility
Home-page: https://github.com/juliabrowser/julia-browser
Author: Harish Santhanalakshmi Ganesan
Author-email: Harish Santhanalakshmi Ganesan <harishsg99@gmail.com>
Project-URL: Homepage, https://github.com/juliabrowser/julia-browser
Project-URL: Bug Reports, https://github.com/juliabrowser/julia-browser/issues
Project-URL: Documentation, https://docs.juliabrowser.com
Project-URL: Source, https://github.com/juliabrowser/julia-browser
Project-URL: Changelog, https://github.com/juliabrowser/julia-browser/blob/main/CHANGELOG.md
Keywords: browser,cli,terminal,web,html,css,javascript,markdown,scraping,automation,headless,spidermonkey,pythonmonkey,web-browser,command-line,text-based
Classifier: Development Status :: 5 - Production/Stable
Classifier: Intended Audience :: Developers
Classifier: Intended Audience :: System Administrators
Classifier: Topic :: Internet :: WWW/HTTP :: Browsers
Classifier: Topic :: Software Development :: Libraries :: Python Modules
Classifier: Topic :: System :: Networking
Classifier: Topic :: Terminals
Classifier: License :: OSI Approved :: MIT License
Classifier: Programming Language :: Python :: 3
Classifier: Programming Language :: Python :: 3.8
Classifier: Programming Language :: Python :: 3.9
Classifier: Programming Language :: Python :: 3.10
Classifier: Programming Language :: Python :: 3.11
Classifier: Programming Language :: Python :: 3.12
Classifier: Operating System :: OS Independent
Classifier: Environment :: Console
Requires-Python: >=3.8
License-File: LICENSE
Requires-Dist: requests>=2.28.0
Requires-Dist: beautifulsoup4>=4.11.0
Requires-Dist: markdownify>=1.0.0
Requires-Dist: pythonmonkey>=1.0.0
Requires-Dist: rich>=13.0.0
Requires-Dist: click>=8.0.0
Requires-Dist: aiohttp>=3.8.0
Requires-Dist: aiosqlite>=0.19.0
Requires-Dist: build>=1.2.2.post1
Requires-Dist: twine>=6.1.0
Requires-Dist: stpyv8>=13.1.201.22
Requires-Dist: wheel>=0.45.1
Requires-Dist: setuptools>=75.3.2
Provides-Extra: dev
Requires-Dist: pytest>=7.0.0; extra == "dev"
Requires-Dist: pytest-cov>=4.0.0; extra == "dev"
Requires-Dist: black>=22.0.0; extra == "dev"
Requires-Dist: flake8>=5.0.0; extra == "dev"
Requires-Dist: mypy>=1.0.0; extra == "dev"
Provides-Extra: performance
Requires-Dist: ujson>=5.0.0; extra == "performance"
Requires-Dist: lxml>=4.9.0; extra == "performance"
Dynamic: author
Dynamic: home-page
Dynamic: license-file
Dynamic: requires-python
